.gitignore
LICENSE
README.md
setup.py
debian/changelog
debian/compat
debian/control
debian/rules
docs/Makefile
docs/make.bat
docs/source/conf.py
docs/source/index.rst
docs/source/modules.rst
docs/source/mosaicomponents.rst
docs/source/setup.rst
docs/source/test.mosaicomponents.rst
docs/source/test.rst
mosaicomponents/__init__.py
mosaicomponents/checkfield.py
mosaicomponents/codefield.py
mosaicomponents/colorfield.py
mosaicomponents/combofield.py
mosaicomponents/commentfield.py
mosaicomponents/field.py
mosaicomponents/floatfield.py
mosaicomponents/iconfield.py
mosaicomponents/intfield.py
mosaicomponents/openfilefield.py
mosaicomponents/savefilefield.py
mosaicomponents/stringfield.py
mosaicomponents.egg-info/PKG-INFO
mosaicomponents.egg-info/SOURCES.txt
mosaicomponents.egg-info/dependency_links.txt
mosaicomponents.egg-info/top_level.txt
test/__init__.py
test/mosaicomponents/__init__.py
test/mosaicomponents/test_checkfield.py
test/mosaicomponents/test_colorfield.py
test/mosaicomponents/test_combofield.py
test/mosaicomponents/test_commentfield.py
test/mosaicomponents/test_field.py
test/mosaicomponents/test_floatfield.py
test/mosaicomponents/test_intfield.py
test/mosaicomponents/test_openfilefield.py
test/mosaicomponents/test_savefilefield.py
test/mosaicomponents/test_stringfield.py